dogratian_usb_sensors/__init__.py
dogratian_usb_sensors-1.1.dist-info/LICENSE
dogratian_usb_sensors-1.1.dist-info/METADATA
dogratian_usb_sensors-1.1.dist-info/WHEEL
dogratian_usb_sensors-1.1.dist-info/top_level.txt
dogratian_usb_sensors-1.1.dist-info/RECORD
