Metadata-Version: 2.1
Name: dogratian-usb-sensors
Version: 1.1
Summary: Pythonic library for Dogratian USB sensors
Home-page: https://github.com/netinvent/dogratian_usb_sensors
Author: NetInvent - Orsiris de Jong
Author-email: contact@netinvent.fr
License: BSD
Keywords: sensor,temperature,humidity,pressure,usb
Classifier: Development Status :: 5 - Production/Stable
Classifier: Intended Audience :: Developers
Classifier: Topic :: Software Development
Classifier: Topic :: System
Classifier: Topic :: System :: Operating System
Classifier: Topic :: System :: Shells
Classifier: Programming Language :: Python
Classifier: Programming Language :: Python :: 3
Classifier: Programming Language :: Python :: Implementation :: CPython
Classifier: Programming Language :: Python :: Implementation :: PyPy
Classifier: Operating System :: POSIX :: Linux
Classifier: Operating System :: POSIX :: BSD :: FreeBSD
Classifier: Operating System :: POSIX :: BSD :: NetBSD
Classifier: Operating System :: POSIX :: BSD :: OpenBSD
Classifier: Operating System :: Microsoft
Classifier: Operating System :: Microsoft :: Windows
Classifier: License :: OSI Approved :: BSD License
License-File: LICENSE
Requires-Dist: pyserial
